Metadata-Version: 2.1
Name: targetd-client
Version: 0.4.0
Summary: A client library for targetd
Home-page: https://gitlab.com/Arcaik/targetd_client
Author: Johan Fleury
Author-email: jfleury@arcaik.net
License: OSI Approved :: GNU Lesser General Public License v3 or later (LGPLv3+)
Platform: any
Classifier: Development Status :: 4 - Beta
Classifier: Environment :: Console
Classifier: Intended Audience :: Developers
Classifier: Intended Audience :: System Administrators
Classifier: License :: OSI Approved :: GNU Lesser General Public License v3 or later (LGPLv3+)
Classifier: Natural Language :: English
Classifier: Operating System :: POSIX
Classifier: Operating System :: POSIX :: Linux
Classifier: Programming Language :: Python
Classifier: Programming Language :: Python :: 3
Classifier: Programming Language :: Python :: 3.6
Classifier: Programming Language :: Python :: 3.7
Classifier: Programming Language :: Python :: 3.8
Classifier: Topic :: System
Classifier: Topic :: System :: Filesystems
Classifier: Topic :: Utilities
Classifier: Typing :: Typed
Requires-Python: >=3.6
Provides-Extra: cli
